[
  {
    "object": "block",
    "id": "939340eb-73a3-4dd3-8b01-d6dd3b203eec",
    "parent": {
      "type": "page_id",
      "page_id": "4553dcd1-6866-4730-aa87-23e1cace3d7e"
    },
    "created_time": "2023-01-06T14:23:00.000Z",
    "last_edited_time": "2023-02-24T03:17:00.000Z",
    "created_by": {
      "object": "user",
      "id": "e0446ede-dde6-457c-b535-d2b19f40b45a"
    },
    "last_edited_by": {
      "object": "user",
      "id": "e0446ede-dde6-457c-b535-d2b19f40b45a"
    },
    "has_children": false,
    "archived": false,
    "type": "heading_2",
    "heading_2": {
      "rich_text": [
        {
          "type": "text",
          "text": { "content": "新着記事", "link": null },
          "annotations": {
            "bold": false,
            "italic": false,
            "strikethrough": false,
            "underline": false,
            "code": false,
            "color": "default"
          },
          "plain_text": "新着記事",
          "href": null
        }
      ],
      "is_toggleable": false,
      "color": "default"
    }
  },
  {
    "object": "block",
    "id": "0c610de6-533f-47c2-a6b3-aa38d306ee79",
    "parent": {
      "type": "page_id",
      "page_id": "4553dcd1-6866-4730-aa87-23e1cace3d7e"
    },
    "created_time": "2023-01-06T09:03:00.000Z",
    "last_edited_time": "2023-03-18T12:29:00.000Z",
    "created_by": {
      "object": "user",
      "id": "e0446ede-dde6-457c-b535-d2b19f40b45a"
    },
    "last_edited_by": {
      "object": "user",
      "id": "e0446ede-dde6-457c-b535-d2b19f40b45a"
    },
    "has_children": false,
    "archived": false,
    "type": "child_database",
    "child_database": { "title": "記事一覧" }
  },
  {
    "object": "block",
    "id": "f1f6bc96-c6c5-43ec-8499-d516b615ad66",
    "parent": {
      "type": "page_id",
      "page_id": "4553dcd1-6866-4730-aa87-23e1cace3d7e"
    },
    "created_time": "2023-01-07T10:24:00.000Z",
    "last_edited_time": "2023-02-24T03:17:00.000Z",
    "created_by": {
      "object": "user",
      "id": "e0446ede-dde6-457c-b535-d2b19f40b45a"
    },
    "last_edited_by": {
      "object": "user",
      "id": "e0446ede-dde6-457c-b535-d2b19f40b45a"
    },
    "has_children": false,
    "archived": false,
    "type": "heading_2",
    "heading_2": {
      "rich_text": [
        {
          "type": "text",
          "text": { "content": "最近読んだ本", "link": null },
          "annotations": {
            "bold": false,
            "italic": false,
            "strikethrough": false,
            "underline": false,
            "code": false,
            "color": "default"
          },
          "plain_text": "最近読んだ本",
          "href": null
        }
      ],
      "is_toggleable": false,
      "color": "default"
    }
  },
  {
    "object": "block",
    "id": "9a9dd691-c392-48a0-98ca-eb596b76ddc4",
    "parent": {
      "type": "page_id",
      "page_id": "4553dcd1-6866-4730-aa87-23e1cace3d7e"
    },
    "created_time": "2023-02-24T03:17:00.000Z",
    "last_edited_time": "2023-03-18T05:30:00.000Z",
    "created_by": {
      "object": "user",
      "id": "e0446ede-dde6-457c-b535-d2b19f40b45a"
    },
    "last_edited_by": {
      "object": "user",
      "id": "e0446ede-dde6-457c-b535-d2b19f40b45a"
    },
    "has_children": false,
    "archived": false,
    "type": "heading_2",
    "heading_2": {
      "rich_text": [
        {
          "type": "text",
          "text": { "content": "プロフィール", "link": null },
          "annotations": {
            "bold": false,
            "italic": false,
            "strikethrough": false,
            "underline": false,
            "code": false,
            "color": "default"
          },
          "plain_text": "プロフィール",
          "href": null
        }
      ],
      "is_toggleable": false,
      "color": "default"
    }
  },
  {
    "object": "block",
    "id": "8780b290-ad42-418f-a714-3819c10d3007",
    "parent": {
      "type": "page_id",
      "page_id": "4553dcd1-6866-4730-aa87-23e1cace3d7e"
    },
    "created_time": "2023-02-24T03:17:00.000Z",
    "last_edited_time": "2023-03-18T05:30:00.000Z",
    "created_by": {
      "object": "user",
      "id": "e0446ede-dde6-457c-b535-d2b19f40b45a"
    },
    "last_edited_by": {
      "object": "user",
      "id": "e0446ede-dde6-457c-b535-d2b19f40b45a"
    },
    "has_children": false,
    "archived": false,
    "type": "image",
    "image": {
      "caption": [],
      "type": "external",
      "external": {
        "url": "https://avatars.githubusercontent.com/u/22557372?s=400&u=77b45945edd9880bce8d4acb60e7460cdc1e5d0a&v=4"
      }
    }
  },
  {
    "object": "block",
    "id": "2e822b82-615e-4cbd-a942-2f5b7886e887",
    "parent": {
      "type": "page_id",
      "page_id": "4553dcd1-6866-4730-aa87-23e1cace3d7e"
    },
    "created_time": "2023-02-24T03:17:00.000Z",
    "last_edited_time": "2023-03-18T05:30:00.000Z",
    "created_by": {
      "object": "user",
      "id": "e0446ede-dde6-457c-b535-d2b19f40b45a"
    },
    "last_edited_by": {
      "object": "user",
      "id": "e0446ede-dde6-457c-b535-d2b19f40b45a"
    },
    "has_children": false,
    "archived": false,
    "type": "paragraph",
    "paragraph": {
      "rich_text": [
        {
          "type": "text",
          "text": {
            "content": "UD(@udus122)",
            "link": { "url": "/6da383059b304e9fafb821c25553c19f" }
          },
          "annotations": {
            "bold": false,
            "italic": false,
            "strikethrough": false,
            "underline": false,
            "code": false,
            "color": "default"
          },
          "plain_text": "UD(@udus122)",
          "href": "/6da383059b304e9fafb821c25553c19f"
        }
      ],
      "color": "default"
    }
  },
  {
    "object": "block",
    "id": "c1b8be76-1e94-4cbe-8518-4a18e6a3cb8d",
    "parent": {
      "type": "page_id",
      "page_id": "4553dcd1-6866-4730-aa87-23e1cace3d7e"
    },
    "created_time": "2023-02-24T03:17:00.000Z",
    "last_edited_time": "2023-03-18T05:30:00.000Z",
    "created_by": {
      "object": "user",
      "id": "e0446ede-dde6-457c-b535-d2b19f40b45a"
    },
    "last_edited_by": {
      "object": "user",
      "id": "e0446ede-dde6-457c-b535-d2b19f40b45a"
    },
    "has_children": false,
    "archived": false,
    "type": "synced_block",
    "synced_block": {
      "synced_from": {
        "type": "block_id",
        "block_id": "8c8b9fd3-d61b-42da-9998-dbc7e3034565"
      },
      "children": []
    }
  },
  {
    "object": "block",
    "id": "160acc69-bcb3-4fe6-983d-f151b848d8ca",
    "parent": {
      "type": "page_id",
      "page_id": "4553dcd1-6866-4730-aa87-23e1cace3d7e"
    },
    "created_time": "2022-12-25T09:08:00.000Z",
    "last_edited_time": "2023-03-18T12:30:00.000Z",
    "created_by": {
      "object": "user",
      "id": "e0446ede-dde6-457c-b535-d2b19f40b45a"
    },
    "last_edited_by": {
      "object": "user",
      "id": "e0446ede-dde6-457c-b535-d2b19f40b45a"
    },
    "has_children": false,
    "archived": false,
    "type": "child_database",
    "child_database": { "title": "文献一覧" }
  },
  {
    "object": "block",
    "id": "7ae02fd9-3da0-4d34-a205-01d4c6452a5b",
    "parent": {
      "type": "page_id",
      "page_id": "4553dcd1-6866-4730-aa87-23e1cace3d7e"
    },
    "created_time": "2023-01-07T05:25:00.000Z",
    "last_edited_time": "2023-03-18T12:30:00.000Z",
    "created_by": {
      "object": "user",
      "id": "e0446ede-dde6-457c-b535-d2b19f40b45a"
    },
    "last_edited_by": {
      "object": "user",
      "id": "e0446ede-dde6-457c-b535-d2b19f40b45a"
    },
    "has_children": false,
    "archived": false,
    "type": "child_database",
    "child_database": { "title": "タグ一覧" }
  },
  {
    "object": "block",
    "id": "72c92885-3af5-4ca9-bc2e-fb75ff316353",
    "parent": {
      "type": "page_id",
      "page_id": "4553dcd1-6866-4730-aa87-23e1cace3d7e"
    },
    "created_time": "2023-03-18T12:30:00.000Z",
    "last_edited_time": "2023-03-18T12:30:00.000Z",
    "created_by": {
      "object": "user",
      "id": "e0446ede-dde6-457c-b535-d2b19f40b45a"
    },
    "last_edited_by": {
      "object": "user",
      "id": "e0446ede-dde6-457c-b535-d2b19f40b45a"
    },
    "has_children": false,
    "archived": false,
    "type": "paragraph",
    "paragraph": { "rich_text": [], "color": "default" }
  }
]
